__init__.py
netkiller/__init__.py
netkiller/data.py
netkiller/fishbone.py
netkiller/gantt.py
netkiller/markdown.py
netkiller/mindmap.py
netkiller/workload.py
netkiller/svg/ScalableVectorGraphics.py
netkiller/svg/__init__.py
netkiller/svg/color.py
netkiller/svg/defs.py
netkiller/svg/elements.py
netkiller/svg/filter.py
netkiller/svg/font.py
netkiller/svg/gradient.py
netkiller_chart-0.4.7.dist-info/licenses/LICENSE
netkiller_chart-0.4.7.dist-info/METADATA
netkiller_chart-0.4.7.dist-info/WHEEL
netkiller_chart-0.4.7.dist-info/entry_points.txt
netkiller_chart-0.4.7.dist-info/top_level.txt
netkiller_chart-0.4.7.dist-info/RECORD
