Metadata-Version: 2.4
Name: netkiller-chart
Version: 0.4.7
Summary: Netkiller Chart(Mindmap,Gantt,Fishbone(Ishikawa Diagram),SVG)
Author-email: Neo <netkiller@msn.com>
License-Expression: MIT
Project-URL: Homepage, https://www.netkiller.cn
Project-URL: Issues, https://github.com/netkiller/netkiller-chart/issues
Classifier: Programming Language :: Python :: 3
Classifier: Operating System :: OS Independent
Requires-Python: >=3.12
License-File: LICENSE
Requires-Dist: drawsvg
Requires-Dist: svgwrite
Requires-Dist: pillow
Requires-Dist: xmind
Dynamic: license-file
